.anltk.mesonpy.libs/pkgconfig/anltk.pc
anltk/__init__.py
anltk/anltk.py
anltk/anltk_pybind.cpython-312-x86_64-linux-gnu.so
anltk/version.py
anltk/constants/__init__.py
anltk/constants/constants.py
anltk/tests/dummy.py
anltk/tests/utils_tests.py
anltk-1.0.8.data/headers/anltk/anltk.hpp
anltk-1.0.8.dist-info/METADATA
anltk-1.0.8.dist-info/WHEEL
anltk-1.0.8.dist-info/RECORD
