Metadata-Version: 2.1
Name: anltk
Version: 1.0.8
Summary: Arabic Natural Language Toolkit (ANLTK)
Keywords: NLP,Arabic,python,arabic,c++
Author-Email: Abdullah Alattar <abdullah.mohammad.alattar@gmail.com>
License: Boost Software License 1.0
Classifier: Development Status :: 4 - Beta
Classifier: Intended Audience :: Developers
Classifier: Intended Audience :: Science/Research
Classifier: Programming Language :: Python :: 3
Classifier: Programming Language :: Python :: 3.7
Classifier: Programming Language :: Python :: 3.8
Classifier: Programming Language :: Python :: 3.9
Classifier: Programming Language :: Python :: 3.10
Classifier: Programming Language :: Python :: 3.11
Classifier: Programming Language :: Python :: 3.12
Classifier: Programming Language :: Python :: 3.13
Classifier: Programming Language :: Python :: 3.14
Classifier: Topic :: Software Development
Classifier: Topic :: Scientific/Engineering
Classifier: Topic :: Scientific/Engineering :: Artificial Intelligence
Classifier: Natural Language :: Arabic
Classifier: Operating System :: Microsoft :: Windows
Classifier: Operating System :: POSIX
Classifier: Operating System :: Unix
Classifier: Operating System :: MacOS
Project-URL: Homepage, https://github.com/Abdullah-AlAttar/anltk
Project-URL: Source, https://github.com/Abdullah-AlAttar/anltk
Project-URL: Bug Tracker, https://github.com/Abdullah-AlAttar/anltk/issues
Requires-Python: >=3.7
